mathbib/__init__.py
mathbib/__main__.py
mathbib/bibtex.py
mathbib/citegen.py
mathbib/command.py
mathbib/partition.py
mathbib/record.py
mathbib/remote/__init__.py
mathbib/remote/arxiv.py
mathbib/remote/doi.py
mathbib/remote/error.py
mathbib/remote/isbn.py
mathbib/remote/ol.py
mathbib/remote/utils.py
mathbib/remote/zbl.py
mathbib/remote/zbmath.py
mathbib/request.py
mathbib/resources/__init__.py
mathbib/resources/journal_abbrevs.json
mathbib/session.py
mathbib/term.py
mathbib-0.7.13.dist-info/LICENSE
mathbib-0.7.13.dist-info/METADATA
mathbib-0.7.13.dist-info/WHEEL
mathbib-0.7.13.dist-info/entry_points.txt
mathbib-0.7.13.dist-info/RECORD
