Metadata-Version: 2.1
Name: mathbib
Version: 0.7.13
Summary: A mathematics BibLaTeX bibliography manager.
Home-page: https://github.com/alexrutar/mathbib-py
License: MIT
Author: Alex Rutar
Author-email: alex@rutar.org
Requires-Python: >=3.12.0,<4.0.0
Classifier: License :: OSI Approved :: MIT License
Classifier: Programming Language :: Python :: 3
Classifier: Programming Language :: Python :: 3.12
Requires-Dist: beautifulsoup4 (>=4.12.3,<5.0.0)
Requires-Dist: bibtexparser (>=1.4.1,<2.0.0)
Requires-Dist: click (>=8.1.7,<9.0.0)
Requires-Dist: lxml (>=5.2.2,<6.0.0)
Requires-Dist: nameparser (>=1.1.3,<2.0.0)
Requires-Dist: python-stdnum (>=1.20,<2.0)
Requires-Dist: requests (>=2.32.3,<3.0.0)
Requires-Dist: tomli-w (>=1.0.0,<2.0.0)
Requires-Dist: urllib3 (>=2.2.2,<3.0.0)
Requires-Dist: xdg-base-dirs (>=6.0.1,<7.0.0)
Project-URL: Repository, https://github.com/alexrutar/mathbib-py
